anndata_validator/__init__.py
anndata_validator/validator.py
hubmap_anndata_validator-1.0.0.dist-info/LICENSE
hubmap_anndata_validator-1.0.0.dist-info/METADATA
hubmap_anndata_validator-1.0.0.dist-info/WHEEL
hubmap_anndata_validator-1.0.0.dist-info/top_level.txt
hubmap_anndata_validator-1.0.0.dist-info/RECORD
