Metadata-Version: 2.1
Name: hubmap-anndata-validator
Version: 1.0.0
Summary: A tool for validating AnnData objects for HuBMAP EPICs.
Home-page: https://github.com/hubmapconsortium/anndata-validator
Author: Penny Cuda
Author-email: Penny Cuda <pcuda@andrew.cmu.edu>
License: GNU General Public License v3 (GPLv3)
Classifier: Programming Language :: Python :: 3
Classifier: License :: OSI Approved :: GNU General Public License v3 (GPLv3)
Classifier: Operating System :: OS Independent
Requires-Python: >=3.8
License-File: LICENSE
Requires-Dist: anndata
